openai_ratelimiter/__init__.py
openai_ratelimiter/base.py
openai_ratelimiter/defs.py
openai_ratelimiter/asyncio/__init__.py
openai_ratelimiter/asyncio/base.py
openai_ratelimiter/asyncio/defs.py
openai_ratelimiter-0.8.2.dist-info/licenses/LICENSE
openai_ratelimiter-0.8.2.dist-info/METADATA
openai_ratelimiter-0.8.2.dist-info/WHEEL
openai_ratelimiter-0.8.2.dist-info/top_level.txt
openai_ratelimiter-0.8.2.dist-info/RECORD
