Metadata-Version: 2.4
Name: openai-ratelimiter
Version: 0.8.2
Summary: A Python module that provides rate limiting capabilities for the OpenAI API, utilizing Redis as a caching service. It helps to manage API usage to avoid exceeding OpenAI's rate limits.
Home-page: https://github.com/blaze-Youssef/openai-ratelimiter
Author: Youssef Benhammouda
Author-email: youssef@benhammouda.ma
License: MIT
Classifier: Development Status :: 3 - Alpha
Classifier: License :: OSI Approved :: MIT License
Classifier: Programming Language :: Python :: 3
Classifier: Programming Language :: Python :: 3.9
Classifier: Programming Language :: Python :: 3.10
Classifier: Programming Language :: Python :: 3.11
Classifier: Programming Language :: Python :: 3.12
License-File: LICENSE
Requires-Dist: redis==5.2.1
Requires-Dist: tiktoken==0.9.0
Dynamic: author
Dynamic: author-email
Dynamic: classifier
Dynamic: description
Dynamic: description-content-type
Dynamic: home-page
Dynamic: license
Dynamic: license-file
Dynamic: requires-dist
Dynamic: summary
